{
    "bustime-response": {
        "prd": [
            {
                "tmstmp": "20240528 10:42",
                "typ": "A",
                "stpnm": "EAST BUSWAY + HOMEWOOD STATION C",
                "stpid": "8154",
                "vid": "3215",
                "dstp": 15165,
                "rt": "P1",
                "rtdd": "P1",
                "rtdir": "INBOUND",
                "des": "DOWNTOWN",
                "prdtm": "20240528 10:49",
                "tablockid": "P1  -319",
                "tatripid": "10381",
                "origtatripno": "14086539",
                "dly": false,
                "dyn": 0,
                "prdctdn": "6",
                "zone": "",
                "psgld": "EMPTY",
                "stst": 38400,
                "stsd": "2024-05-28",
                "flagstop": 0
            },
            {
                "tmstmp": "20240528 10:42",
                "typ": "A",
                "stpnm": "EAST BUSWAY + HOMEWOOD STATION C",
                "stpid": "8154",
                "vid": "3209",
                "dstp": 17018,
                "rt": "P3",
                "rtdd": "P3",
                "rtdir": "INBOUND",
                "des": "OAKLAND",
                "prdtm": "20240528 10:56",
                "tablockid": "P3  -373",
                "tatripid": "10384",
                "origtatripno": "14085306",
                "dly": false,
                "dyn": 0,
                "prdctdn": "14",
                "zone": "",
                "psgld": "EMPTY",
                "stst": 38940,
                "stsd": "2024-05-28",
                "flagstop": 0
            },
            {
                "tmstmp": "20240528 10:42",
                "typ": "A",
                "stpnm": "FIFTH AVE + PENN AVE FS",
                "stpid": "20014",
                "vid": "6460",
                "dstp": 19020,
                "rt": "71D",
                "rtdd": "71D",
                "rtdir": "INBOUND",
                "des": "OAKLAND",
                "prdtm": "20240528 10:58",
                "tablockid": "71D-160",
                "tatripid": "10828",
                "origtatripno": "14085360",
                "dly": false,
                "dyn": 0,
                "prdctdn": "15",
                "zone": "",
                "psgld": "EMPTY",
                "stst": 38280,
                "stsd": "2024-05-28",
                "flagstop": 0
            },
            {
                "tmstmp": "20240528 10:42",
                "typ": "A",
                "stpnm": "EAST BUSWAY + HOMEWOOD STATION C",
                "stpid": "8154",
                "vid": "3316",
                "dstp": 17091,
                "rt": "P1",
                "rtdd": "P1",
                "rtdir": "INBOUND",
                "des": "DOWNTOWN",
                "prdtm": "20240528 11:03",
                "tablockid": "P1  -315",
                "tatripid": "10385",
                "origtatripno": "14086540",
                "dly": false,
                "dyn": 0,
                "prdctdn": "20",
                "zone": "",
                "psgld": "EMPTY",
                "stst": 39300,
                "stsd": "2024-05-28",
                "flagstop": 0
            },
            {
                "tmstmp": "20240528 10:42",
                "typ": "A",
                "stpnm": "FIFTH AVE + PENN AVE FS",
                "stpid": "20014",
                "vid": "6112",
                "dstp": 15749,
                "rt": "71D",
                "rtdd": "71D",
                "rtdir": "INBOUND",
                "des": "OAKLAND",
                "prdtm": "20240528 11:12",
                "tablockid": "71D-157",
                "tatripid": "10832",
                "origtatripno": "14084967",
                "dly": false,
                "dyn": 0,
                "prdctdn": "29",
                "zone": "",
                "psgld": "EMPTY",
                "stst": 39480,
                "stsd": "2024-05-28",
                "flagstop": 0
            }
        ]
    }
}